{
    "('airplane', 0)": {
        "mmcl": [
            332.5696128145083,
            8.472404780470043
        ],
        "rvcl": [
            394.01493210083186,
            62.25134390472955
        ],
        "regular_cl": [
            315.1979851963926,
            30.344949201881224
        ]
    },
    "('airplane', 1)": {
        "mmcl": [
            448.6903850427096,
            42.471161634354544
        ],
        "rvcl": [
            473.46837346229387,
            126.31951429838628
        ],
        "regular_cl": [
            350.4155579598898,
            92.1497120263494
        ]
    },
    "('airplane', 2)": {
        "mmcl": [
            434.6982850577973,
            75.07482285371015
        ],
        "rvcl": [
            444.95779205786755,
            116.48646415776578
        ],
        "regular_cl": [
            312.1268854973347,
            44.05013455453117
        ]
    },
    "('airplane', 3)": {
        "mmcl": [
            350.13338860051664,
            27.521709762730495
        ],
        "rvcl": [
            408.15834732391266,
            29.568554145055543
        ],
        "regular_cl": [
            311.1040369489918,
            28.781371094897423
        ]
    },
    "('airplane', 4)": {
        "mmcl": [
            554.6104975529888,
            177.5544770184365
        ],
        "rvcl": [
            431.97067163266047,
            51.485296418171856
        ],
        "regular_cl": [
            335.7121897368587,
            57.126964288855824
        ]
    },
    "('automobile', 0)": {
        "mmcl": [
            661.0956214040019,
            347.86589816681345
        ],
        "rvcl": [
            471.29959194525,
            78.15029182529047
        ],
        "regular_cl": [
            374.36253555974037,
            72.87114044399566
        ]
    },
    "('automobile', 1)": {
        "mmcl": [
            558.2038172136146,
            164.93678474059493
        ],
        "rvcl": [
            444.59103639938087,
            27.30278329250537
        ],
        "regular_cl": [
            306.8466659060709,
            31.006907956740317
        ]
    },
    "('automobile', 2)": {
        "mmcl": [
            495.8109203739051,
            67.94259213750621
        ],
        "rvcl": [
            477.91178498023027,
            30.644412416320638
        ],
        "regular_cl": [
            345.17669007374934,
            40.18723077721788
        ]
    },
    "('automobile', 3)": {
        "mmcl": [
            697.0201958241657,
            326.6604708936995
        ],
        "rvcl": [
            446.4350544792484,
            29.52198444439936
        ],
        "regular_cl": [
            325.5393372892975,
            14.633551929034612
        ]
    },
    "('automobile', 4)": {
        "mmcl": [
            724.8146572899126,
            164.75792701561966
        ],
        "rvcl": [
            578.1728411826323,
            86.05754975183696
        ],
        "regular_cl": [
            422.66687659839135,
            71.07474329815064
        ]
    },
    "('bird', 0)": {
        "mmcl": [
            873.0816498133881,
            387.1061282336438
        ],
        "rvcl": [
            490.1428680166553,
            140.54351448750265
        ],
        "regular_cl": [
            360.31483460688634,
            157.86515647690678
        ]
    },
    "('bird', 1)": {
        "mmcl": [
            330.23165266040013,
            5.906048762508535
        ],
        "rvcl": [
            378.0464930430504,
            73.4835357582343
        ],
        "regular_cl": [
            307.0769429247244,
            36.79045320969913
        ]
    },
    "('bird', 2)": {
        "mmcl": [
            623.5594334959504,
            216.01898323720528
        ],
        "rvcl": [
            432.6913820808771,
            30.99676526245185
        ],
        "regular_cl": [
            327.14109587166,
            29.792839554416364
        ]
    },
    "('bird', 3)": {
        "mmcl": [
            1613.0824675719618,
            1346.8426695362841
        ],
        "rvcl": [
            514.6472360206897,
            94.90172360115194
        ],
        "regular_cl": [
            359.33310938368294,
            58.813965772528704
        ]
    },
    "('bird', 4)": {
        "mmcl": [
            807.0558545181268,
            411.5647440970323
        ],
        "rvcl": [
            435.26958284880095,
            100.90485539048859
        ],
        "regular_cl": [
            337.4350270059435,
            102.64534377896025
        ]
    },
    "('cat', 0)": {
        "mmcl": [
            671.9644349797177,
            101.02082352100082
        ],
        "rvcl": [
            452.7987255562483,
            45.618897838444674
        ],
        "regular_cl": [
            356.4462770584611,
            75.3945318193044
        ]
    },
    "('cat', 1)": {
        "mmcl": [
            691.0398077329402,
            156.33634078724322
        ],
        "rvcl": [
            492.21193162756015,
            78.79743437985702
        ],
        "regular_cl": [
            348.0944408193549,
            60.38300657485638
        ]
    },
    "('cat', 2)": {
        "mmcl": [
            1396.3593958096867,
            764.6541923209597
        ],
        "rvcl": [
            502.37968837988126,
            102.77361064936748
        ],
        "regular_cl": [
            408.74340885644335,
            107.12239015802736
        ]
    },
    "('cat', 3)": {
        "mmcl": [
            1256.224966429602,
            1118.0650906668359
        ],
        "rvcl": [
            479.7417917709239,
            74.91373734032139
        ],
        "regular_cl": [
            365.9506007050647,
            65.52949155238606
        ]
    },
    "('cat', 4)": {
        "mmcl": [
            774.509905144689,
            331.193145188989
        ],
        "rvcl": [
            488.07137223246775,
            111.53876456836059
        ],
        "regular_cl": [
            340.9522187924471,
            71.2831317078202
        ]
    },
    "('deer', 0)": {
        "mmcl": [
            837.2581207940532,
            380.80418610214656
        ],
        "rvcl": [
            490.5707725063033,
            127.44268667538131
        ],
        "regular_cl": [
            362.2977911284366,
            108.19030214313996
        ]
    },
    "('deer', 1)": {
        "mmcl": [
            946.9657324105694,
            509.57265071347535
        ],
        "rvcl": [
            476.16825647699477,
            95.03150152154531
        ],
        "regular_cl": [
            346.38501017399466,
            104.2295457502914
        ]
    },
    "('deer', 2)": {
        "mmcl": [
            1187.7451088191524,
            615.2782769390001
        ],
        "rvcl": [
            435.808182660899,
            29.283984568891473
        ],
        "regular_cl": [
            321.46908527778675,
            46.97485137317471
        ]
    },
    "('deer', 3)": {
        "mmcl": [
            566.925786321551,
            63.42798600338819
        ],
        "rvcl": [
            403.1686340404196,
            30.207485213939755
        ],
        "regular_cl": [
            313.8380040533758,
            26.913140939305737
        ]
    },
    "('deer', 4)": {
        "mmcl": [
            2049.2322160202957,
            1622.015645705526
        ],
        "rvcl": [
            456.63466922278656,
            104.5031192360532
        ],
        "regular_cl": [
            335.15385563779796,
            73.32320159607703
        ]
    },
    "('dog', 0)": {
        "mmcl": [
            756.0115113675615,
            155.8075273514497
        ],
        "rvcl": [
            465.08223740834,
            55.39382720457684
        ],
        "regular_cl": [
            327.8267628809151,
            26.998721614866863
        ]
    },
    "('dog', 1)": {
        "mmcl": [
            524.177563595782,
            179.556679150028
        ],
        "rvcl": [
            438.97492301687396,
            39.94730623546806
        ],
        "regular_cl": [
            317.36480204125684,
            45.73044813696934
        ]
    },
    "('dog', 2)": {
        "mmcl": [
            625.6418710594183,
            169.93667640283675
        ],
        "rvcl": [
            492.96212179855445,
            71.05040989749946
        ],
        "regular_cl": [
            323.9414678574284,
            34.63994321413406
        ]
    },
    "('dog', 3)": {
        "mmcl": [
            610.2632580035296,
            166.55293440153812
        ],
        "rvcl": [
            444.89770668664084,
            69.56600545675843
        ],
        "regular_cl": [
            327.8381058166255,
            42.330385672171836
        ]
    },
    "('dog', 4)": {
        "mmcl": [
            928.0222361180644,
            446.87884501951584
        ],
        "rvcl": [
            471.85812986323134,
            90.45656033782502
        ],
        "regular_cl": [
            378.96111867267956,
            108.54182179977734
        ]
    },
    "('frog', 0)": {
        "mmcl": [
            737.1273213781333,
            185.37037914552837
        ],
        "rvcl": [
            468.96796808163697,
            82.577102749638
        ],
        "regular_cl": [
            323.4790535901378,
            61.10528415220534
        ]
    },
    "('frog', 1)": {
        "mmcl": [
            1316.5301247597556,
            1075.2769665724195
        ],
        "rvcl": [
            502.2232859197387,
            128.54546999095982
        ],
        "regular_cl": [
            324.6000239873466,
            77.74189676547694
        ]
    },
    "('frog', 2)": {
        "mmcl": [
            541.2846647834124,
            126.99422171715597
        ],
        "rvcl": [
            393.7174731428332,
            31.674506863438687
        ],
        "regular_cl": [
            297.20636820084826,
            26.285075775854903
        ]
    },
    "('frog', 3)": {
        "mmcl": [
            2189.569884454112,
            2592.0999798773373
        ],
        "rvcl": [
            469.7046157082944,
            74.99086857867375
        ],
        "regular_cl": [
            332.1642253530923,
            32.384875218685266
        ]
    },
    "('frog', 4)": {
        "mmcl": [
            672.0106765795001,
            229.44584319319398
        ],
        "rvcl": [
            420.2819408684544,
            53.508694753156696
        ],
        "regular_cl": [
            320.75130869766286,
            48.11925441363437
        ]
    },
    "('horse', 0)": {
        "mmcl": [
            985.9323670765219,
            701.9637358451363
        ],
        "rvcl": [
            426.6012120976123,
            91.45472097772786
        ],
        "regular_cl": [
            298.30286074691304,
            41.74450960652889
        ]
    },
    "('horse', 1)": {
        "mmcl": [
            647.3476006180622,
            220.759884951486
        ],
        "rvcl": [
            412.3269489594615,
            50.20845793779505
        ],
        "regular_cl": [
            306.03749569396393,
            33.99247419386902
        ]
    },
    "('horse', 2)": {
        "mmcl": [
            1658.1994160501697,
            586.7113265539301
        ],
        "rvcl": [
            547.8739947571789,
            116.83205849029835
        ],
        "regular_cl": [
            348.44010777989763,
            59.14214548492046
        ]
    },
    "('horse', 3)": {
        "mmcl": [
            768.718816377709,
            310.52435944700795
        ],
        "rvcl": [
            565.1509622387796,
            90.08546975099001
        ],
        "regular_cl": [
            362.3507690905973,
            62.813413824080676
        ]
    },
    "('horse', 4)": {
        "mmcl": [
            2423.858500496998,
            1955.5968152309686
        ],
        "rvcl": [
            485.8289673932836,
            37.879306572567806
        ],
        "regular_cl": [
            346.7295158121372,
            39.25130868563865
        ]
    },
    "('ship', 0)": {
        "mmcl": [
            726.2490711371908,
            284.38996692760935
        ],
        "rvcl": [
            492.3487749367094,
            81.94932730076617
        ],
        "regular_cl": [
            366.1584395407276,
            73.1942325544149
        ]
    },
    "('ship', 1)": {
        "mmcl": [
            656.1528319708456,
            135.8901233679031
        ],
        "rvcl": [
            564.6244978903756,
            106.48126877909023
        ],
        "regular_cl": [
            438.0099598515948,
            97.42810448243611
        ]
    },
    "('ship', 2)": {
        "mmcl": [
            573.4503986196876,
            114.81221855018431
        ],
        "rvcl": [
            375.0725924334438,
            46.903979133086686
        ],
        "regular_cl": [
            297.14792347433524,
            28.52508162501434
        ]
    },
    "('ship', 3)": {
        "mmcl": [
            762.773104131397,
            547.3500078212744
        ],
        "rvcl": [
            449.5894929868483,
            86.06183242542559
        ],
        "regular_cl": [
            409.4997139177732,
            159.43207652336284
        ]
    },
    "('ship', 4)": {
        "mmcl": [
            378.17354273417834,
            15.626841942872902
        ],
        "rvcl": [
            450.9546385813167,
            34.15709470013496
        ],
        "regular_cl": [
            300.71144082487433,
            18.46898916271481
        ]
    },
    "('truck', 0)": {
        "mmcl": [
            434.02363337785226,
            43.12702819971554
        ],
        "rvcl": [
            388.1622029886741,
            35.42725484794454
        ],
        "regular_cl": [
            282.961199461767,
            40.4137957751119
        ]
    },
    "('truck', 1)": {
        "mmcl": [
            704.687526474545,
            334.3312871659853
        ],
        "rvcl": [
            502.3893533411857,
            117.92597241838308
        ],
        "regular_cl": [
            318.30945298862673,
            46.65972313030699
        ]
    },
    "('truck', 2)": {
        "mmcl": [
            529.6241955881167,
            108.94203383635872
        ],
        "rvcl": [
            524.7187722825422,
            104.30794432090842
        ],
        "regular_cl": [
            343.1523808549717,
            49.15896259211532
        ]
    },
    "('truck', 3)": {
        "mmcl": [
            460.8048634213175,
            87.22522730847162
        ],
        "rvcl": [
            422.0141046962969,
            40.15812446492994
        ],
        "regular_cl": [
            328.0115683428894,
            39.01658339358899
        ]
    },
    "('truck', 4)": {
        "mmcl": [
            604.7480139078076,
            280.4379308522494
        ],
        "rvcl": [
            439.78647428995646,
            69.43140625386117
        ],
        "regular_cl": [
            320.2420834888759,
            38.20390606734125
        ]
    }
}