{
    "norm": Infinity,
    "model": "cnn_4layer_b",
    "batch_size": 256,
    "mmcl_model": "cnn_4layer_b",
    "mmcl_checkpoint": "models/mmcl/rbf/cnn_4layer_b_C_1_rbf_auto.pkl",
    "rvcl_model": "cnn_4layer_b_adv",
    "rvcl_checkpoint": "models/unsupervised/cifar10_cnn_4layer_b_adv2.pkl",
    "regular_cl_model": "cnn_4layer_b",
    "regular_cl_checkpoint": "models/regular_cl/regular_cl_cnn_4layer_b_bs_32_lr_1e-3.pkl",
    "train_type": "contrastive",
    "dataset": "cifar-10",
    "name": "",
    "seed": 1,
    "color_jitter_strength": 0.5,
    "temperature": 0.5,
    "attack_type": "linf",
    "target_eps": 0.06274509803921569,
    "alpha": 0.001,
    "k": 150,
    "random_start": true,
    "loss_type": "mse",
    "mini_batch": 10,
    "max_steps": 100,
    "negatives_per_class": 2,
    "positives_per_class": 5,
    "average_robust_radius": {
        "cat": [
            {
                "mmcl": 0.031099396693718973,
                "rvcl": 0.04444549500167088,
                "regular_cl": 0.027092940673077867
            },
            {
                "mmcl": 0.042858652707119894,
                "rvcl": 0.05740260034621593,
                "regular_cl": 0.04913837369688028
            },
            {
                "mmcl": 0.04254226244736654,
                "rvcl": 0.06071053324167982,
                "regular_cl": 0.05138705664822712
            },
            {
                "mmcl": 0.04792362819848171,
                "rvcl": 0.05830378219930784,
                "regular_cl": 0.040936650162500934
            },
            {
                "mmcl": 0.04681207000724422,
                "rvcl": 0.05975015128377158,
                "regular_cl": 0.03968982735408923
            }
        ],
        "ship": [
            {
                "mmcl": 0.050992442215639734,
                "rvcl": 0.06870419889695414,
                "regular_cl": 0.052708768859619996
            },
            {
                "mmcl": 0.03884057263156314,
                "rvcl": 0.0638726572952919,
                "regular_cl": 0.0522057902866714
            },
            {
                "mmcl": 0.143959505530265,
                "rvcl": 0.07948643086289546,
                "regular_cl": 0.05268196366194565
            },
            {
                "mmcl": 0.1523500087980286,
                "rvcl": 0.0683483313140856,
                "regular_cl": 0.05030478091226895
            },
            {
                "mmcl": 0.04989787547079535,
                "rvcl": 0.056759243842318736,
                "regular_cl": 0.04592298860476123
            }
        ],
        "airplane": [
            {
                "mmcl": 0.16134861528838781,
                "rvcl": 0.07212478349401863,
                "regular_cl": 0.06094822293290589
            },
            {
                "mmcl": 0.07299357043996856,
                "rvcl": 0.04897951161303303,
                "regular_cl": 0.04266930129890372
            },
            {
                "mmcl": 0.03691698210129996,
                "rvcl": 0.0339859734783469,
                "regular_cl": 0.026408899976975892
            },
            {
                "mmcl": 0.0802089643310132,
                "rvcl": 0.10323440681528634,
                "regular_cl": 0.10674137783139612
            },
            {
                "mmcl": 0.03211913755500796,
                "rvcl": 0.043059850488241916,
                "regular_cl": 0.036756532031808495
            }
        ],
        "frog": [
            {
                "mmcl": 0.041957375574889336,
                "rvcl": 0.050115429504052775,
                "regular_cl": 0.034028436214473205
            },
            {
                "mmcl": 0.04581716524143076,
                "rvcl": 0.05965925498549672,
                "regular_cl": 0.04553539306872128
            },
            {
                "mmcl": 0.033489886763094195,
                "rvcl": 0.031560897081640685,
                "regular_cl": 0.024906665557548675
            },
            {
                "mmcl": 0.05342980962123218,
                "rvcl": 0.05675031936299825,
                "regular_cl": 0.03763109924550337
            },
            {
                "mmcl": 0.062459064234524755,
                "rvcl": 0.047220087038668784,
                "regular_cl": 0.037064505967647515
            }
        ],
        "automobile": [
            {
                "mmcl": 0.0405953285281334,
                "rvcl": 0.0583712080697612,
                "regular_cl": 0.04669808439770248
            },
            {
                "mmcl": 0.04757077778833718,
                "rvcl": 0.05916135796660961,
                "regular_cl": 0.047245018413282956
            },
            {
                "mmcl": 0.052173331860103644,
                "rvcl": 0.07089647659821846,
                "regular_cl": 0.05683187830568512
            },
            {
                "mmcl": 0.043685897948617165,
                "rvcl": 0.06002468224194343,
                "regular_cl": 0.047403975776268856
            },
            {
                "mmcl": 0.05194189883231578,
                "rvcl": 0.07270277850879994,
                "regular_cl": 0.04548619727346351
            }
        ],
        "truck": [
            {
                "mmcl": 0.041671633438069317,
                "rvcl": 0.054660212658082706,
                "regular_cl": 0.0422096429743293
            },
            {
                "mmcl": 0.06126312048615369,
                "rvcl": 0.0712450712068365,
                "regular_cl": 0.04993620944424669
            },
            {
                "mmcl": 0.05409498504788088,
                "rvcl": 0.057194351908833596,
                "regular_cl": 0.04604707380300018
            },
            {
                "mmcl": 0.038947571104270336,
                "rvcl": 0.05175238862553518,
                "regular_cl": 0.041062799742077355
            },
            {
                "mmcl": 0.04301668903843216,
                "rvcl": 0.06732265138648724,
                "regular_cl": 0.04549836124349819
            }
        ],
        "dog": [
            {
                "mmcl": 0.04752034336427692,
                "rvcl": 0.0724959592584974,
                "regular_cl": 0.057798707485308874
            },
            {
                "mmcl": 0.05422704193405378,
                "rvcl": 0.06868676281458067,
                "regular_cl": 0.0478356855535051
            },
            {
                "mmcl": 0.040183246253459655,
                "rvcl": 0.051214347329562315,
                "regular_cl": 0.039770306466538036
            },
            {
                "mmcl": 0.0319962909855715,
                "rvcl": 0.03916569681235968,
                "regular_cl": 0.029879252044130073
            },
            {
                "mmcl": 0.04379149899395745,
                "rvcl": 0.05715134925758826,
                "regular_cl": 0.04699745145134986
            }
        ],
        "horse": [
            {
                "mmcl": 0.04646976382177728,
                "rvcl": 0.05681644308522335,
                "regular_cl": 0.03405848090286175
            },
            {
                "mmcl": 0.07919605180799433,
                "rvcl": 0.05162503217686915,
                "regular_cl": 0.03680245657663919
            },
            {
                "mmcl": 0.029339972119354723,
                "rvcl": 0.03439468922345491,
                "regular_cl": 0.02767722411101027
            },
            {
                "mmcl": 0.05387574774984058,
                "rvcl": 0.07015101261739826,
                "regular_cl": 0.05521495956303271
            },
            {
                "mmcl": 0.053999451831524915,
                "rvcl": 0.06373812315151402,
                "regular_cl": 0.05215348203955096
            }
        ],
        "deer": [
            {
                "mmcl": 0.0316884758482969,
                "rvcl": 0.03284437059872087,
                "regular_cl": 0.022510585778705818
            },
            {
                "mmcl": 0.03501810062766077,
                "rvcl": 0.03785589449329842,
                "regular_cl": 0.026890059627172985
            },
            {
                "mmcl": 0.03907289493131177,
                "rvcl": 0.04606863864804862,
                "regular_cl": 0.03311321656828644
            },
            {
                "mmcl": 0.04861649809476552,
                "rvcl": 0.04445362548816926,
                "regular_cl": 0.028525875398991554
            },
            {
                "mmcl": 0.05449410935969783,
                "rvcl": 0.04767091616306137,
                "regular_cl": 0.03690488165069104
            }
        ],
        "bird": [
            {
                "mmcl": 0.07440887852523145,
                "rvcl": 0.07665346447361622,
                "regular_cl": 0.04959523716672089
            },
            {
                "mmcl": 0.03977345067811358,
                "rvcl": 0.06069001646715656,
                "regular_cl": 0.03832196827987547
            },
            {
                "mmcl": 0.055833130614612654,
                "rvcl": 0.05441931523585532,
                "regular_cl": 0.039085376498475294
            },
            {
                "mmcl": 0.06536577667712133,
                "rvcl": 0.08341024811061162,
                "regular_cl": 0.06010824204654202
            },
            {
                "mmcl": 0.04886568480205571,
                "rvcl": 0.0523570617991393,
                "regular_cl": 0.043161576848610314
            }
        ]
    }
}